.gitignore
LICENSE
README.md
requirements.txt
encryptedsocket/__init__.py
encryptedsocket/client.py
encryptedsocket/server.py
encryptedsocket/utils.py
encryptedsocket-3.0.0.dist-info/LICENSE
encryptedsocket-3.0.0.dist-info/METADATA
encryptedsocket-3.0.0.dist-info/WHEEL
encryptedsocket-3.0.0.dist-info/top_level.txt
encryptedsocket-3.0.0.dist-info/RECORD
